odoo9_addon_hr_holidays_legal_leave-9.0.1.0.0.99.dev12-py2.7-nspkg.pth
odoo9_addon_hr_holidays_legal_leave-9.0.1.0.0.99.dev12.dist-info/DESCRIPTION.rst
odoo9_addon_hr_holidays_legal_leave-9.0.1.0.0.99.dev12.dist-info/METADATA
odoo9_addon_hr_holidays_legal_leave-9.0.1.0.0.99.dev12.dist-info/RECORD
odoo9_addon_hr_holidays_legal_leave-9.0.1.0.0.99.dev12.dist-info/WHEEL
odoo9_addon_hr_holidays_legal_leave-9.0.1.0.0.99.dev12.dist-info/metadata.json
odoo9_addon_hr_holidays_legal_leave-9.0.1.0.0.99.dev12.dist-info/namespace_packages.txt
odoo9_addon_hr_holidays_legal_leave-9.0.1.0.0.99.dev12.dist-info/top_level.txt
odoo_addons/hr_holidays_legal_leave/README.rst
odoo_addons/hr_holidays_legal_leave/__init__.py
odoo_addons/hr_holidays_legal_leave/__openerp__.py
odoo_addons/hr_holidays_legal_leave/i18n/ar.po
odoo_addons/hr_holidays_legal_leave/i18n/de.po
odoo_addons/hr_holidays_legal_leave/i18n/es.po
odoo_addons/hr_holidays_legal_leave/i18n/fi.po
odoo_addons/hr_holidays_legal_leave/i18n/fr.po
odoo_addons/hr_holidays_legal_leave/i18n/fr_CH.po
odoo_addons/hr_holidays_legal_leave/i18n/hr_holidays_legal_leave.pot
odoo_addons/hr_holidays_legal_leave/i18n/it.po
odoo_addons/hr_holidays_legal_leave/i18n/nl_NL.po
odoo_addons/hr_holidays_legal_leave/i18n/pt_BR.po
odoo_addons/hr_holidays_legal_leave/i18n/ro.po
odoo_addons/hr_holidays_legal_leave/i18n/sl.po
odoo_addons/hr_holidays_legal_leave/models/__init__.py
odoo_addons/hr_holidays_legal_leave/models/hr_employee.py
odoo_addons/hr_holidays_legal_leave/models/hr_holidays_status.py
odoo_addons/hr_holidays_legal_leave/models/res_company.py
odoo_addons/hr_holidays_legal_leave/static/description/icon.png
odoo_addons/hr_holidays_legal_leave/tests/__init__.py
odoo_addons/hr_holidays_legal_leave/tests/test_holidays_legal_leave.py
odoo_addons/hr_holidays_legal_leave/views/hr_holidays_status.xml
